README.md
setup.py
darkbox/__init__.py
darkbox/darkbox.py
darkbox.egg-info/PKG-INFO
darkbox.egg-info/SOURCES.txt
darkbox.egg-info/dependency_links.txt
darkbox.egg-info/entry_points.txt
darkbox.egg-info/requires.txt
darkbox.egg-info/top_level.txt
darkbox/commands/__init__.py
darkbox/commands/base64.py
darkbox/commands/cat.py
darkbox/commands/cp.py
darkbox/commands/curl.py
darkbox/commands/exip.py
darkbox/commands/factor.py
darkbox/commands/false.py
darkbox/commands/fold.py
darkbox/commands/head.py
darkbox/commands/hostname.py
darkbox/commands/ls.py
darkbox/commands/md5sum.py
darkbox/commands/mv.py
darkbox/commands/nmap.py
darkbox/commands/package.py
darkbox/commands/pwd.py
darkbox/commands/rm.py
darkbox/commands/sha224sum.py
darkbox/commands/sha256sum.py
darkbox/commands/sha384sum.py
darkbox/commands/sha512sum.py
darkbox/commands/tac.py
darkbox/commands/template.py
darkbox/commands/true.py
darkbox/commands/uniq.py
darkbox/commands/unzip.py
darkbox/commands/wc.py
darkbox/commands/xxd.py
darkbox/commands/yes.py
darkbox/commands/zip.py
darkbox/static/__init__.py
darkbox/static/ports.py
darkbox/util/__init__.py
darkbox/util/osutil.py