Metadata-Version: 2.1
Name: darkbox
Version: 0.1.0
Summary: Portable, all-in-one, cross-platform toolkit.
Home-page: https://github.com/AbnormalSec/darkbox
Author: AbnormalSec
Author-email: vesche@protonmail.com
License: WTFPL
Platform: UNKNOWN
Classifier: Development Status :: 2 - Pre-Alpha
Classifier: Environment :: Console
Classifier: Intended Audience :: Information Technology
Classifier: License :: Public Domain
Classifier: Programming Language :: Python :: 3
Classifier: Programming Language :: Python :: 3.9
Classifier: Topic :: Security
